odach/__init__.py
odach/nms.py
odach/oda.py
odach/wbf.py
odach-0.3.0.dist-info/LICENSE
odach-0.3.0.dist-info/METADATA
odach-0.3.0.dist-info/WHEEL
odach-0.3.0.dist-info/top_level.txt
odach-0.3.0.dist-info/RECORD
