Metadata-Version: 2.1
Name: odach
Version: 0.3.0
Summary: ODAch is a test-time-augmentation tool for pytorch 2d object detectors with YOLO support.
Home-page: https://github.com/kentaroy47/ODA-Object-Detection-ttA
Author: Kentaro Yoshioka
Author-email: Kentaro Yoshioka <meathouse47@gmail.com>
Maintainer-email: Kentaro Yoshioka <meathouse47@gmail.com>
License: MIT
Project-URL: Homepage, https://github.com/kentaroy47/ODA-Object-Detection-ttA
Project-URL: Documentation, https://github.com/kentaroy47/ODA-Object-Detection-ttA#readme
Project-URL: Repository, https://github.com/kentaroy47/ODA-Object-Detection-ttA
Project-URL: Bug Tracker, https://github.com/kentaroy47/ODA-Object-Detection-ttA/issues
Keywords: object-detection,pytorch,tta,test-time-augmentation,yolo,computer-vision
Classifier: Development Status :: 4 - Beta
Classifier: Intended Audience :: Developers
Classifier: Intended Audience :: Science/Research
Classifier: License :: OSI Approved :: MIT License
Classifier: Operating System :: OS Independent
Classifier: Programming Language :: Python :: 3
Classifier: Programming Language :: Python :: 3.7
Classifier: Programming Language :: Python :: 3.8
Classifier: Programming Language :: Python :: 3.9
Classifier: Programming Language :: Python :: 3.10
Classifier: Programming Language :: Python :: 3.11
Classifier: Topic :: Scientific/Engineering :: Artificial Intelligence
Classifier: Topic :: Scientific/Engineering :: Image Processing
Classifier: Topic :: Software Development :: Libraries :: Python Modules
Requires-Python: >=3.7
License-File: LICENSE
Requires-Dist: torch >=1.7.0
Requires-Dist: numpy >=1.19.0
Requires-Dist: numba >=0.50.0
Requires-Dist: ultralytics >=8.0.0
Requires-Dist: Pillow >=8.0.0
Requires-Dist: torchvision >=0.8.0
